publicity_idl/__init__.py
publicity_idl/context.py
publicity_idl/domain.py
publicity_idl/enum.py
publicity_idl/exception.py
publicity_idl/repo.py
publicity_idl-0.1.3.dist-info/METADATA
publicity_idl-0.1.3.dist-info/WHEEL
publicity_idl-0.1.3.dist-info/licenses/LICENSE
publicity_idl-0.1.3.dist-info/RECORD
