Metadata-Version: 2.4
Name: publicity_idl
Version: 0.1.3
Summary: 商讯/舆情 项目数据模型、常量定义
Project-URL: GitLab XMU Group, https://git.xmu.edu.cn/innovation
Project-URL: Documentation, https://kcn67g8bllja.feishu.cn/wiki/Utr8wiXK9igQwfk2H8OcSIJAnNd
Author-email: AnUpdatingHam <1319716110@qq.com>
License: Copyright (c) 2018 The Python Packaging Authority
License-File: LICENSE
Keywords: idl,publicity,publicity_idl
Requires-Python: >=3.11
Requires-Dist: dataclasses
Requires-Dist: pydantic
Requires-Dist: sqlalchemy
Requires-Dist: sqlalchemy-serializer
